odoo/addons/stock_demand_estimate/README.rst
odoo/addons/stock_demand_estimate/__init__.py
odoo/addons/stock_demand_estimate/__manifest__.py
odoo/addons/stock_demand_estimate/i18n/am.po
odoo/addons/stock_demand_estimate/i18n/ar.po
odoo/addons/stock_demand_estimate/i18n/bg.po
odoo/addons/stock_demand_estimate/i18n/bs.po
odoo/addons/stock_demand_estimate/i18n/ca.po
odoo/addons/stock_demand_estimate/i18n/ca_ES.po
odoo/addons/stock_demand_estimate/i18n/cs.po
odoo/addons/stock_demand_estimate/i18n/da.po
odoo/addons/stock_demand_estimate/i18n/de.po
odoo/addons/stock_demand_estimate/i18n/el_GR.po
odoo/addons/stock_demand_estimate/i18n/en_AU.po
odoo/addons/stock_demand_estimate/i18n/en_GB.po
odoo/addons/stock_demand_estimate/i18n/es.po
odoo/addons/stock_demand_estimate/i18n/es_AR.po
odoo/addons/stock_demand_estimate/i18n/es_CL.po
odoo/addons/stock_demand_estimate/i18n/es_CO.po
odoo/addons/stock_demand_estimate/i18n/es_CR.po
odoo/addons/stock_demand_estimate/i18n/es_DO.po
odoo/addons/stock_demand_estimate/i18n/es_EC.po
odoo/addons/stock_demand_estimate/i18n/es_ES.po
odoo/addons/stock_demand_estimate/i18n/es_MX.po
odoo/addons/stock_demand_estimate/i18n/es_PE.po
odoo/addons/stock_demand_estimate/i18n/es_PY.po
odoo/addons/stock_demand_estimate/i18n/es_VE.po
odoo/addons/stock_demand_estimate/i18n/et.po
odoo/addons/stock_demand_estimate/i18n/eu.po
odoo/addons/stock_demand_estimate/i18n/fa.po
odoo/addons/stock_demand_estimate/i18n/fi.po
odoo/addons/stock_demand_estimate/i18n/fr.po
odoo/addons/stock_demand_estimate/i18n/fr_CA.po
odoo/addons/stock_demand_estimate/i18n/fr_CH.po
odoo/addons/stock_demand_estimate/i18n/fr_FR.po
odoo/addons/stock_demand_estimate/i18n/gl.po
odoo/addons/stock_demand_estimate/i18n/gl_ES.po
odoo/addons/stock_demand_estimate/i18n/he.po
odoo/addons/stock_demand_estimate/i18n/hi.po
odoo/addons/stock_demand_estimate/i18n/hr.po
odoo/addons/stock_demand_estimate/i18n/hr_HR.po
odoo/addons/stock_demand_estimate/i18n/hu.po
odoo11_addon_stock_demand_estimate-11.0.1.1.0.dist-info/DESCRIPTION.rst
odoo11_addon_stock_demand_estimate-11.0.1.1.0.dist-info/METADATA
odoo11_addon_stock_demand_estimate-11.0.1.1.0.dist-info/RECORD
odoo11_addon_stock_demand_estimate-11.0.1.1.0.dist-info/WHEEL
odoo11_addon_stock_demand_estimate-11.0.1.1.0.dist-info/metadata.json
odoo11_addon_stock_demand_estimate-11.0.1.1.0.dist-info/top_level.txt
